<?xml version="1.0" encoding="utf-8"?>
<SoundBanksInfo Platform="Mac" BasePlatform="Mac" SchemaVersion="11" SoundbankVersion="118">
	<RootPaths>
		<ProjectRoot>C:\Users\nefas\Poly\polyminis-unity\Assets\Wwise\Project\polyminis\</ProjectRoot>
		<SourceFilesRoot>C:\Users\nefas\Poly\polyminis-unity\Assets\Wwise\Project\polyminis\.cache\Mac\</SourceFilesRoot>
		<SoundBanksRoot>C:\Users\nefas\Poly\polyminis-unity\Assets\StreamingAssets\Audio\GeneratedSoundBanks\Mac\</SoundBanksRoot>
		<ExternalSourcesInputFile></ExternalSourcesInputFile>
		<ExternalSourcesOutputRoot>C:\Users\nefas\Poly\polyminis-unity\Assets\Wwise\Project\polyminis\GeneratedSoundBanks\Mac\</ExternalSourcesOutputRoot>
	</RootPaths>
	<DialogueEvents/>
	<StreamedFiles>
		<File Id="29796930" Language="SFX">
			<ShortName>Exploration First.wav</ShortName>
			<Path>SFX\Exploration First_4B8CC0C5.wem</Path>
		</File>
		<File Id="71673649" Language="SFX">
			<ShortName>Intro Theme First.wav</ShortName>
			<Path>SFX\Intro Theme First_4B8CC0C5.wem</Path>
		</File>
		<File Id="401293344" Language="SFX">
			<ShortName>Species Design First.wav</ShortName>
			<Path>SFX\Species Design First_4B8CC0C5.wem</Path>
		</File>
		<File Id="584759446" Language="SFX">
			<ShortName>Species Design Loop.wav</ShortName>
			<Path>SFX\Species Design Loop_4B8CC0C5.wem</Path>
		</File>
		<File Id="585421635" Language="SFX">
			<ShortName>Creature Observation.wav</ShortName>
			<Path>SFX\Creature Observation_4B8CC0C5.wem</Path>
		</File>
		<File Id="796678487" Language="SFX">
			<ShortName>Exploration Loop.wav</ShortName>
			<Path>SFX\Exploration Loop_4B8CC0C5.wem</Path>
		</File>
		<File Id="1066362763" Language="SFX">
			<ShortName>Intro Theme Loop.wav</ShortName>
			<Path>SFX\Intro Theme Loop_4B8CC0C5.wem</Path>
		</File>
	</StreamedFiles>
	<MediaFilesNotInAnyBank/>
	<SoundBanks>
		<SoundBank Id="393239870" Language="SFX">
			<ObjectPath>\SoundBanks\Default Work Unit\SFX</ObjectPath>
			<ShortName>SFX</ShortName>
			<Path>SFX.bnk</Path>
			<IncludedEvents>
				<Event Id="2187412920" Name="P_UI_Accepted" ObjectPath="\Events\Default Work Unit\SFX_Wu\UI_Wu\P_UI_Accepted"/>
				<Event Id="4094348196" Name="P_UI_Add" ObjectPath="\Events\Default Work Unit\SFX_Wu\UI_Wu\P_UI_Add"/>
				<Event Id="2258750257" Name="P_UI_Cancel" ObjectPath="\Events\Default Work Unit\SFX_Wu\UI_Wu\P_UI_Cancel"/>
				<Event Id="2903831199" Name="P_UI_Data" ObjectPath="\Events\Default Work Unit\SFX_Wu\UI_Wu\P_UI_Data"/>
				<Event Id="3781701507" Name="P_UI_Error" ObjectPath="\Events\Default Work Unit\SFX_Wu\UI_Wu\P_UI_Error"/>
				<Event Id="2141736205" Name="P_UI_Ok" ObjectPath="\Events\Default Work Unit\SFX_Wu\UI_Wu\P_UI_Ok"/>
				<Event Id="2581921037" Name="P_UI_Return" ObjectPath="\Events\Default Work Unit\SFX_Wu\UI_Wu\P_UI_Return"/>
				<Event Id="2374130668" Name="P_UI_Substract" ObjectPath="\Events\Default Work Unit\SFX_Wu\UI_Wu\P_UI_Substract"/>
				<Event Id="1935057997" Name="P_UI_Warning" ObjectPath="\Events\Default Work Unit\SFX_Wu\UI_Wu\P_UI_Warning"/>
				<Event Id="4058515758" Name="P_Woosh" ObjectPath="\Events\Default Work Unit\SFX_Wu\Spaceship_Wu\P_Woosh"/>
			</IncludedEvents>
			<IncludedMemoryFiles>
				<File Id="22748774" Language="SFX">
					<ShortName>UI_PACK_01\UI_OK.wav</ShortName>
					<Path>SFX\UI_PACK_01\UI_OK_9E69E797.wem</Path>
				</File>
				<File Id="32637561" Language="SFX">
					<ShortName>SF-CK Data GUI Single 01.wav</ShortName>
					<Path>SFX\SF-CK Data GUI Single 01_0CE4E06B.wem</Path>
				</File>
				<File Id="105738243" Language="SFX">
					<ShortName>UI_PACK_01\UI_WARNING.wav</ShortName>
					<Path>SFX\UI_PACK_01\UI_WARNING_9E69E797.wem</Path>
				</File>
				<File Id="269566149" Language="SFX">
					<ShortName>whoosh01.wav</ShortName>
					<Path>SFX\whoosh01_9E69E797.wem</Path>
				</File>
				<File Id="299834042" Language="SFX">
					<ShortName>UI_PACK_01\UI_CANCEL.wav</ShortName>
					<Path>SFX\UI_PACK_01\UI_CANCEL_9E69E797.wem</Path>
				</File>
				<File Id="309805726" Language="SFX">
					<ShortName>SF-CK Data GUI Single 01.wav</ShortName>
					<Path>SFX\SF-CK Data GUI Single 01_B91C577D.wem</Path>
				</File>
				<File Id="566911207" Language="SFX">
					<ShortName>SF-CK Data GUI Single 01.wav</ShortName>
					<Path>SFX\SF-CK Data GUI Single 01_7D786894.wem</Path>
				</File>
				<File Id="662412231" Language="SFX">
					<ShortName>SF-CK Data GUI Single 01.wav</ShortName>
					<Path>SFX\SF-CK Data GUI Single 01_1F3B888F.wem</Path>
				</File>
				<File Id="792914303" Language="SFX">
					<ShortName>UI_PACK_01\UI_ACCEPTED.wav</ShortName>
					<Path>SFX\UI_PACK_01\UI_ACCEPTED_9E69E797.wem</Path>
				</File>
				<File Id="812774060" Language="SFX">
					<ShortName>SF-CK Data GUI Single 01.wav</ShortName>
					<Path>SFX\SF-CK Data GUI Single 01_91E1B6CA.wem</Path>
				</File>
				<File Id="973505296" Language="SFX">
					<ShortName>UI_PACK_01\UI_AWESOME.wav</ShortName>
					<Path>SFX\UI_PACK_01\UI_AWESOME_9E69E797.wem</Path>
				</File>
			</IncludedMemoryFiles>
		</SoundBank>
		<SoundBank Id="1355168291" Language="SFX">
			<ObjectPath>Init</ObjectPath>
			<ShortName>Init</ShortName>
			<Path>Init.bnk</Path>
		</SoundBank>
		<SoundBank Id="3991942870" Language="SFX">
			<ObjectPath>\SoundBanks\Default Work Unit\Music</ObjectPath>
			<ShortName>Music</ShortName>
			<Path>Music.bnk</Path>
			<IncludedEvents>
				<Event Id="369775550" Name="Play_creature_observation" ObjectPath="\Events\Default Work Unit\Music_Wu\Play_creature_observation"/>
				<Event Id="2287072429" Name="Play_exploration" ObjectPath="\Events\Default Work Unit\Music_Wu\Play_exploration"/>
				<Event Id="2290104414" Name="Play_intro_theme" ObjectPath="\Events\Default Work Unit\Music_Wu\Play_intro_theme"/>
				<Event Id="585562449" Name="Play_species_design" ObjectPath="\Events\Default Work Unit\Music_Wu\Play_species_design"/>
			</IncludedEvents>
			<ReferencedStreamedFiles>
				<File Id="29796930"/>
				<File Id="71673649"/>
				<File Id="401293344"/>
				<File Id="584759446"/>
				<File Id="585421635"/>
				<File Id="796678487"/>
				<File Id="1066362763"/>
			</ReferencedStreamedFiles>
		</SoundBank>
	</SoundBanks>
</SoundBanksInfo>
